my_model/__init__.py
my_model/model.py
my_model/py.typed
ds_my_model-1.3.3.dist-info/LICENSE.md
ds_my_model-1.3.3.dist-info/METADATA
ds_my_model-1.3.3.dist-info/WHEEL
ds_my_model-1.3.3.dist-info/RECORD
