Metadata-Version: 2.1
Name: ds-my-model
Version: 1.3.3
Summary: The data model for the My project
License: MIT
Author: Daryl Stark
Author-email: daryl@dstark.nl
Requires-Python: >=3.10,<4.0
Classifier: License :: OSI Approved :: MIT License
Classifier: Programming Language :: Python :: 3
Classifier: Programming Language :: Python :: 3.10
Classifier: Programming Language :: Python :: 3.11
Classifier: Programming Language :: Python :: 3.12
Requires-Dist: argon2-cffi (>=21.3.0,<22.0.0)
Requires-Dist: passlib (>=1.7.4,<2.0.0)
Requires-Dist: pydantic (>=2.5.2,<3.0.0)
Requires-Dist: pyotp (>=2.8.0,<3.0.0)
Requires-Dist: sqlmodel (>=0.0.14,<0.0.15)
